pip_grab/__init__.py
pip_grab/__main__.py
pip_grab/pip_grab.py
pip_grab-1.0.0.6.dist-info/METADATA
pip_grab-1.0.0.6.dist-info/WHEEL
pip_grab-1.0.0.6.dist-info/top_level.txt
pip_grab-1.0.0.6.dist-info/RECORD
